jarvis_cli/__init__.py
jarvis_cli/animations.py
jarvis_cli/cli.py
jarvis_cli/client.py
jarvis_cli/config.py
jarvis_cli/display.py
jarvis_cli/jarvis_client.py
jarvis_cli/logger.py
jarvis_cli/login.py
jarvis_cli/markdown_utils.py
jarvis_cli/models.py
jarvis_cli/session.py
jarvis_cli/themes.py
jvs_cli-0.1.13.dist-info/licenses/LICENSE
jvs_cli-0.1.13.dist-info/METADATA
jvs_cli-0.1.13.dist-info/WHEEL
jvs_cli-0.1.13.dist-info/entry_points.txt
jvs_cli-0.1.13.dist-info/top_level.txt
jvs_cli-0.1.13.dist-info/RECORD
