Metadata-Version: 2.4
Name: jvs-cli
Version: 0.1.13
Summary: Terminal-based AI chat interface with streaming support
Author: JVS CLI Contributors
License: Apache-2.0
Keywords: cli,chat,ai,terminal,streaming
Classifier: Development Status :: 4 - Beta
Classifier: License :: OSI Approved :: Apache Software License
Classifier: Programming Language :: Python :: 3
Classifier: Programming Language :: Python :: 3.10
Classifier: Programming Language :: Python :: 3.11
Classifier: Programming Language :: Python :: 3.12
Requires-Python: >=3.10
License-File: LICENSE
Requires-Dist: typer>=0.9.0
Requires-Dist: rich>=13.0.0
Requires-Dist: prompt-toolkit>=3.0.0
Requires-Dist: httpx>=0.24.0
Requires-Dist: pydantic>=2.0.0
Requires-Dist: orjson>=3.9.0
Requires-Dist: python-dateutil>=2.8.0
Requires-Dist: aiohttp>=3.9.0
Dynamic: license-file
Dynamic: requires-python
